abracatabra/__about__.py
abracatabra/__init__.py
abracatabra/animation_player.py
abracatabra/custom_widget.py
abracatabra/figure_widget.py
abracatabra/keys.py
abracatabra/tab_group_container.py
abracatabra/tabbed_figure_widget.py
abracatabra/tabbed_plot_window.py
abracatabra/icons/abracatabra1.svg
abracatabra/icons/abracatabra2.svg
abracatabra/icons/abracatabra3.svg
abracatabra/icons/tabplot.svg
abracatabra-1.3.0.dist-info/METADATA
abracatabra-1.3.0.dist-info/WHEEL
abracatabra-1.3.0.dist-info/licenses/LICENSE
abracatabra-1.3.0.dist-info/RECORD
