Metadata-Version: 2.4
Name: abracatabra
Version: 1.3.0
Summary: Tabbed plot extension for matplotlib using the Qt backend
Project-URL: Homepage, https://github.com/byu-magicc/abracatabra
Project-URL: Repository, https://github.com/byu-magicc/abracatabra.git
Project-URL: Issues, https://github.com/byu-magicc/abracatabra/issues
Author-email: Mat Haskell <mhaskell9@gmail.com>
License-Expression: BSD-3-Clause
License-File: LICENSE
Keywords: matplotlib,plot,qt,tabbed,tabs,visualization
Classifier: License :: OSI Approved :: BSD License
Classifier: Operating System :: OS Independent
Classifier: Programming Language :: Python :: 3
Requires-Python: >=3.10
Requires-Dist: matplotlib
Provides-Extra: qt-pyqt6
Requires-Dist: pyqt6; extra == 'qt-pyqt6'
Provides-Extra: qt-pyside6
Requires-Dist: pyside6; extra == 'qt-pyside6'
